vectoria/__init__.py
vectoria/compressor.py
vectoria_compressor-0.1.0.dist-info/licenses/LICENSE
vectoria_compressor-0.1.0.dist-info/METADATA
vectoria_compressor-0.1.0.dist-info/WHEEL
vectoria_compressor-0.1.0.dist-info/top_level.txt
vectoria_compressor-0.1.0.dist-info/RECORD
