Metadata-Version: 2.4
Name: vectoria-compressor
Version: 0.1.0
Summary: An adaptive vector quantization compressor.
Author-email: John Drossos <john@johndrossos.com>
Classifier: Programming Language :: Python :: 3
Classifier: License :: OSI Approved :: MIT License
Classifier: Operating System :: OS Independent
Requires-Python: >=3.8
License-File: LICENSE
Dynamic: license-file
